hidp_django_admin/README.md
hidp_django_admin/__init__.py
hidp_django_admin/apps.py
hidp_django_admin/static/css/hidp_django_admin.css
hidp_django_admin/static/css/hidp_django_admin_pre_login.css
hidp_django_admin/templates/admin/base.html
hidp_django_admin/templates/hidp/base_post_login.html
hidp_django_admin/templates/hidp/base_pre_login.html
django_hidp_django_admin-1.0.1.dist-info/METADATA
django_hidp_django_admin-1.0.1.dist-info/WHEEL
django_hidp_django_admin-1.0.1.dist-info/top_level.txt
django_hidp_django_admin-1.0.1.dist-info/RECORD
