Metadata-Version: 2.4
Name: django-hidp-django-admin
Version: 1.0.1
Summary: A Django-admin-themed template pack for HIdP
Author-email: Ramon de Jezus <rdejezus@leukeleu.nl>, Wouter de Vries <wdevries@leukeleu.nl>, Robin van Leeuwen <rvanleeuwen@leukeleu.nl>
License-Expression: BSD-3-Clause
Project-URL: Repository, https://github.com/leukeleu/django-hidp-django-admin/
Project-URL: Issues, https://github.com/leukeleu/django-hidp-django-admin/issues
Project-URL: Releasenotes, https://github.com/leukeleu/django-hidp-django-admin/releases
Classifier: Development Status :: 5 - Production/Stable
Classifier: Framework :: Django
Classifier: Intended Audience :: Developers
Classifier: Programming Language :: Python :: 3
Requires-Python: >=3.11
Requires-Dist: django-hidp<2,>=1.4.0
